{"cameraMode":{"drawMode":0,"name":"Shaded","section":"Shading Mode"},"sceneLighting":true,"audioPlay":false,"sceneViewState":{"m_AlwaysRefresh":false,"showFog":true,"showSkybox":true,"showFlares":true,"showImageEffects":true,"showParticleSystems":true,"showVisualEffectGraphs":true,"m_FxEnabled":false},"in2DMode":false,"pivot":{"x":529.94921875,"y":149.17559814453126,"z":-3.2998452186584474},"rotation":{"x":0.032991137355566028,"y":0.013492550700902939,"z":-0.0004452770808711648,"w":0.9993658661842346},"size":184.5135040283203,"orthographic":false}